smartchangelog/__init__.py
smartchangelog/changelog.py
smartchangelog/commit.py
smartchangelog/commitmsg.py
smartchangelog/datetools.py
smartchangelog/gitcmd.py
smartchangelog/githook.py
smartchangelog/tools.py
smartchangelog/scripts/__init__.py
smartchangelog/scripts/changelog_script.py
smartchangelog/scripts/commitmsg_script.py
smartchangelog-0.1.2.dist-info/DESCRIPTION.rst
smartchangelog-0.1.2.dist-info/METADATA
smartchangelog-0.1.2.dist-info/RECORD
smartchangelog-0.1.2.dist-info/WHEEL
smartchangelog-0.1.2.dist-info/entry_points.txt
smartchangelog-0.1.2.dist-info/metadata.json
smartchangelog-0.1.2.dist-info/top_level.txt
tests/integration/__init__.py
tests/integration/test_changelog_script.py
tests/integration/test_commitmsg_script.py
tests/integration/test_githook.py
tests/integration/test_gitusage.py
tests/unit/__init__.py
tests/unit/test_changelog.py
tests/unit/test_commit.py
tests/unit/test_commitmsg.py
tests/unit/test_datetools.py
tests/unit/test_gitcmd.py
tests/unit/test_static_types_check.py
