Metadata-Version: 2.0
Name: smartchangelog
Version: 0.1.2
Summary: tools to generate smart changelog
Home-page: https://github.com/ngouzy/smartchangelog
Author: Nicolas Gouzy
Author-email: nicolas.gouzy@gmail.com
License: MIT
Keywords: changelog,git,hook,message formatter
Platform: UNKNOWN
Classifier: Development Status :: 4 - Beta
Classifier: Intended Audience :: Developers
Classifier: Topic :: Software Development :: Documentation
Classifier: License :: OSI Approved :: MIT License
Classifier: Programming Language :: Python :: 3.6
Classifier: Programming Language :: Python :: 3 :: Only
Classifier: Environment :: Console
Provides-Extra: test
Requires-Dist: mypy; extra == 'test'
Requires-Dist: pytest; extra == 'test'
Requires-Dist: pytest-cov; extra == 'test'
